{
  "$schema": "https://raw.githubusercontent.com/LGUG2Z/komorebi/v0.1.36/schema.json",
  "app_specific_configuration_path": "$Env:USERPROFILE/applications.json",
  "window_hiding_behaviour": "Cloak",
  "cross_monitor_move_behaviour": "Insert",
  "default_workspace_padding": 0,
  "global_work_area_offset": {
    "left": 13,
    "top": 6,
    "right": 22,
    "bottom": 2
  },
  "default_container_padding": 3,
  "border": true,
  "border_width": 5,
  "border_offset": -1,
  "border_style": "Rounded",
  "mouse_follows_focus": true,
  "transparency": false,
  "transparency_alpha": 233,
  "animation": {
    "enabled": false,
    "duration": 250,
    "fps": 48,
    "style": "EaseOutExpo"
  },
  "stackbar": {
    "height": 36,
    "mode": "OnStack",
    "tabs": {
      "width": 200,
      "focused_text": "#ECEFF4",
      "unfocused_text": "#000000",
      "background": "#2E3440",
      "font_family": "CaskaydiaCove NFP"
    },
    "label": "Title"
  },
  "theme": {
    "palette": "Base16",
    "name": "Nord",
    "single_border": "Base0F",
    "unfocused_border": "Base00",
    "floating_border": "Base0A",
    "monocle_border": "Base09"
  },
  "monitors": [
    {
      "workspaces": [
        {
          "name": "I",
          "layout": "BSP"
        }
      ]
    },
    {
      "workspaces": [
        {
          "name": "I",
          "layout": "BSP"
        }
      ]
    }
  ]
}
